llmatic/__init__.py
llmatic/cli.py
llmatic/db.py
llmatic/tracker.py
llmatic/utils.py
llmatic-0.0.1.dist-info/LICENSE
llmatic-0.0.1.dist-info/METADATA
llmatic-0.0.1.dist-info/WHEEL
llmatic-0.0.1.dist-info/entry_points.txt
llmatic-0.0.1.dist-info/RECORD
