Metadata-Version: 2.1
Name: llmatic
Version: 0.0.1
Summary: No BS utilities for developing with LLMs
License: MIT
Author: Agam More
Requires-Python: >=3.8,<4.0
Classifier: License :: OSI Approved :: MIT License
Classifier: Programming Language :: Python :: 3
Classifier: Programming Language :: Python :: 3.8
Classifier: Programming Language :: Python :: 3.9
Classifier: Programming Language :: Python :: 3.10
Classifier: Programming Language :: Python :: 3.11
Classifier: Programming Language :: Python :: 3.12
Requires-Dist: click (>=8.1.7,<9.0.0)
Requires-Dist: tokencost (>=0.1.8,<0.2.0)
